{
	"info": {
		"_postman_id": "budget-api-comprehensive-2025",
		"name": "Comprehensive Budget API Collection",
		"description": "Complete API collection for Personal Budget Application with Zero-Based Budgeting features. This collection includes all budget-related endpoints with sample requests and responses for frontend implementation.",
		"schema": "https://schema.getpostman.com/json/collection/v2.1.0/collection.json"
	},
	"item": [
		{
			"name": "Authentication",
			"item": [
				{
					"name": "Register User",
					"request": {
						"method": "POST",
						"header": [
							{
								"key": "Content-Type",
								"value": "application/json"
							}
						],
						"body": {
							"mode": "raw",
							"raw": "{\n  \"name\": \"John Doe\",\n  \"email\": \"john@example.com\",\n  \"password\": \"password123\",\n  \"password_confirmation\": \"password123\",\n  \"currency_code\": \"USD\",\n  \"timezone\": \"America/New_York\"\n}"
						},
						"url": {
							"raw": "{{base_url}}/api/register",
							"host": [
								"{{base_url}}"
							],
							"path": [
								"api",
								"register"
							]
						},
						"description": "Register a new user account. Returns user data and authentication token."
					},
					"response": [
						{
							"name": "Success Response",
							"originalRequest": {
								"method": "POST",
								"header": [],
								"body": {
									"mode": "raw",
									"raw": "{\n  \"name\": \"John Doe\",\n  \"email\": \"john@example.com\",\n  \"password\": \"password123\",\n  \"password_confirmation\": \"password123\"\n}"
								},
								"url": {
									"raw": "{{base_url}}/api/register",
									"host": [
										"{{base_url}}"
									],
									"path": [
										"api",
										"register"
									]
								}
							},
							"status": "Created",
							"code": 201,
							"_postman_previewlanguage": "json",
							"header": [],
							"cookie": [],
							"body": "{\n  \"success\": true,\n  \"message\": \"User registered successfully\",\n  \"data\": {\n    \"user\": {\n      \"id\": 1,\n      \"name\": \"John Doe\",\n      \"email\": \"john@example.com\",\n      \"currency_code\": \"USD\",\n      \"timezone\": \"America/New_York\",\n      \"created_at\": \"2025-09-07T10:00:00.000000Z\",\n      \"updated_at\": \"2025-09-07T10:00:00.000000Z\"\n    },\n    \"token\": \"1|AbCdEfGhIjKlMnOpQrStUvWxYz\",\n    \"token_type\": \"Bearer\"\n  }\n}"
						}
					]
				},
				{
					"name": "Login User",
					"request": {
						"method": "POST",
						"header": [
							{
								"key": "Content-Type",
								"value": "application/json"
							}
						],
						"body": {
							"mode": "raw",
							"raw": "{\n  \"email\": \"test@example.com\",\n  \"password\": \"password123\"\n}"
						},
						"url": {
							"raw": "{{base_url}}/api/login",
							"host": [
								"{{base_url}}"
							],
							"path": [
								"api",
								"login"
							]
						},
						"description": "Authenticate user and get access token for API calls."
					},
					"response": [
						{
							"name": "Success Response",
							"originalRequest": {
								"method": "POST",
								"header": [],
								"body": {
									"mode": "raw",
									"raw": "{\n  \"email\": \"test@example.com\",\n  \"password\": \"password123\"\n}"
								},
								"url": {
									"raw": "{{base_url}}/api/login",
									"host": [
										"{{base_url}}"
									],
									"path": [
										"api",
										"login"
									]
								}
							},
							"status": "OK",
							"code": 200,
							"_postman_previewlanguage": "json",
							"header": [],
							"cookie": [],
							"body": "{\n  \"success\": true,\n  \"message\": \"Login successful\",\n  \"data\": {\n    \"user\": {\n      \"id\": 1,\n      \"name\": \"Test User\",\n      \"email\": \"test@example.com\",\n      \"email_verified_at\": null,\n      \"created_at\": \"2025-09-06T07:52:50.000000Z\",\n      \"updated_at\": \"2025-09-06T07:52:50.000000Z\",\n      \"currency_code\": \"USD\",\n      \"timezone\": \"UTC\",\n      \"provider\": null,\n      \"provider_id\": null,\n      \"avatar\": null\n    },\n    \"token\": \"38|AccJAcgmEDUGHGnUXRPLkPLCPeNoGFJcmvQLPXsF631d87c7\",\n    \"token_type\": \"Bearer\"\n  }\n}"
						}
					]
				}
			]
		},
		{
			"name": "Budget Management",
			"item": [
				{
					"name": "Get All Budgets",
					"request": {
						"method": "GET",
						"header": [
							{
								"key": "Authorization",
								"value": "Bearer {{auth_token}}"
							},
							{
								"key": "Content-Type",
								"value": "application/json"
							}
						],
						"url": {
							"raw": "{{base_url}}/api/budgets",
							"host": [
								"{{base_url}}"
							],
							"path": [
								"api",
								"budgets"
							]
						},
						"description": "Retrieve all budgets for the authenticated user with summary statistics."
					},
					"response": [
						{
							"name": "Success Response",
							"originalRequest": {
								"method": "GET",
								"header": [],
								"url": {
									"raw": "{{base_url}}/api/budgets",
									"host": [
										"{{base_url}}"
									],
									"path": [
										"api",
										"budgets"
									]
								}
							},
							"status": "OK",
							"code": 200,
							"_postman_previewlanguage": "json",
							"header": [],
							"cookie": [],
							"body": "{\n  \"success\": true,\n  \"message\": \"Budgets retrieved successfully\",\n  \"data\": {\n    \"budgets\": [\n      {\n        \"id\": 6,\n        \"user_id\": 1,\n        \"month\": \"2025-12-01T00:00:00.000000Z\",\n        \"notes\": \"December Test Budget\",\n        \"created_at\": \"2025-09-07T10:26:47.000000Z\",\n        \"updated_at\": \"2025-09-07T10:26:47.000000Z\",\n        \"budget_items\": [],\n        \"incomes\": [],\n        \"expenses\": []\n      }\n    ],\n    \"summary\": {\n      \"total_budgets\": 1,\n      \"current_month_budgets\": 0,\n      \"current_month_planned_amount\": \"0.00\",\n      \"current_month_actual_amount\": \"0.00\",\n      \"current_month_balance\": \"0.00\"\n    }\n  }\n}"
						}
					]
				},
				{
					"name": "Create Budget",
					"request": {
						"method": "POST",
						"header": [
							{
								"key": "Authorization",
								"value": "Bearer {{auth_token}}"
							},
							{
								"key": "Content-Type",
								"value": "application/json"
							}
						],
						"body": {
							"mode": "raw",
							"raw": "{\n  \"month\": \"2025-12-01\",\n  \"notes\": \"December Test Budget\"\n}"
						},
						"url": {
							"raw": "{{base_url}}/api/budgets",
							"host": [
								"{{base_url}}"
							],
							"path": [
								"api",
								"budgets"
							]
						},
						"description": "Create a new budget for a specific month. Month should be in YYYY-MM-DD format (first day of month)."
					},
					"response": [
						{
							"name": "Success Response",
							"originalRequest": {
								"method": "POST",
								"header": [],
								"body": {
									"mode": "raw",
									"raw": "{\n  \"month\": \"2025-12-01\",\n  \"notes\": \"December Test Budget\"\n}"
								},
								"url": {
									"raw": "{{base_url}}/api/budgets",
									"host": [
										"{{base_url}}"
									],
									"path": [
										"api",
										"budgets"
									]
								}
							},
							"status": "Created",
							"code": 201,
							"_postman_previewlanguage": "json",
							"header": [],
							"cookie": [],
							"body": "{\n  \"success\": true,\n  \"message\": \"Budget created successfully\",\n  \"data\": {\n    \"user_id\": 1,\n    \"month\": \"2025-12-01T00:00:00.000000Z\",\n    \"notes\": \"December Test Budget\",\n    \"updated_at\": \"2025-09-07T10:26:47.000000Z\",\n    \"created_at\": \"2025-09-07T10:26:47.000000Z\",\n    \"id\": 6,\n    \"budget_items\": [],\n    \"incomes\": [],\n    \"expenses\": []\n  }\n}"
						}
					]
				},
				{
					"name": "Get Budget Details (Zero-Based Features)",
					"request": {
						"method": "GET",
						"header": [
							{
								"key": "Authorization",
								"value": "Bearer {{auth_token}}"
							},
							{
								"key": "Content-Type",
								"value": "application/json"
							}
						],
						"url": {
							"raw": "{{base_url}}/api/budgets/{{budget_id}}",
							"host": [
								"{{base_url}}"
							],
							"path": [
								"api",
								"budgets",
								"{{budget_id}}"
							]
						},
						"description": "Get detailed budget information including zero-based budgeting metrics, budget health score, and item-level analytics."
					},
					"response": [
						{
							"name": "Success Response with Zero-Based Features",
							"originalRequest": {
								"method": "GET",
								"header": [],
								"url": {
									"raw": "{{base_url}}/api/budgets/6",
									"host": [
										"{{base_url}}"
									],
									"path": [
										"api",
										"budgets",
										"6"
									]
								}
							},
							"status": "OK",
							"code": 200,
							"_postman_previewlanguage": "json",
							"header": [],
							"cookie": [],
							"body": "{\n  \"success\": true,\n  \"message\": \"Budget retrieved successfully\",\n  \"data\": {\n    \"budget\": {\n      \"id\": 6,\n      \"user_id\": 1,\n      \"month\": \"2025-12-01T00:00:00.000000Z\",\n      \"notes\": \"December Test Budget\",\n      \"created_at\": \"2025-09-07T10:26:47.000000Z\",\n      \"updated_at\": \"2025-09-07T10:26:47.000000Z\",\n      \"budget_items\": [],\n      \"incomes\": [],\n      \"expenses\": []\n    },\n    \"summary\": {\n      \"total_planned\": \"0.00\",\n      \"actual_spent\": \"0.00\",\n      \"total_income\": \"0.00\",\n      \"total_expenses\": \"0.00\",\n      \"savings\": \"0.00\",\n      \"balance\": \"0.00\",\n      \"unallocated_income\": \"0.00\",\n      \"over_budget_items_count\": 0,\n      \"under_budget_items_count\": 0,\n      \"budget_health_score\": 100,\n      \"is_zero_based\": true\n    },\n    \"budget_items_health\": []\n  }\n}"
						}
					]
				}
			]
		},
		{
			"name": "Categories",
			"item": [
				{
					"name": "Get All Categories",
					"request": {
						"method": "GET",
						"header": [
							{
								"key": "Authorization",
								"value": "Bearer {{auth_token}}"
							},
							{
								"key": "Content-Type",
								"value": "application/json"
							}
						],
						"url": {
							"raw": "{{base_url}}/api/categories",
							"host": [
								"{{base_url}}"
							],
							"path": [
								"api",
								"categories"
							]
						},
						"description": "Retrieve all categories for the authenticated user."
					}
				},
				{
					"name": "Create Category",
					"request": {
						"method": "POST",
						"header": [
							{
								"key": "Authorization",
								"value": "Bearer {{auth_token}}"
							},
							{
								"key": "Content-Type",
								"value": "application/json"
							}
						],
						"body": {
							"mode": "raw",
							"raw": "{\n  \"name\": \"Food & Dining\",\n  \"type\": \"expense\",\n  \"description\": \"Groceries and restaurant expenses\",\n  \"sort_order\": 1,\n  \"is_default\": false\n}"
						},
						"url": {
							"raw": "{{base_url}}/api/categories",
							"host": [
								"{{base_url}}"
							],
							"path": [
								"api",
								"categories"
							]
						},
						"description": "Create a new expense or income category. Type can be 'expense' or 'income'."
					},
					"response": [
						{
							"name": "Success Response",
							"originalRequest": {
								"method": "POST",
								"header": [],
								"body": {
									"mode": "raw",
									"raw": "{\n  \"name\": \"Food & Dining\",\n  \"type\": \"expense\",\n  \"description\": \"Groceries and restaurant expenses\",\n  \"sort_order\": 1,\n  \"is_default\": false\n}"
								},
								"url": {
									"raw": "{{base_url}}/api/categories",
									"host": [
										"{{base_url}}"
									],
									"path": [
										"api",
										"categories"
									]
								}
							},
							"status": "Created",
							"code": 201,
							"_postman_previewlanguage": "json",
							"header": [],
							"cookie": [],
							"body": "{\n  \"success\": true,\n  \"message\": \"Category created successfully\",\n  \"data\": {\n    \"user_id\": 1,\n    \"name\": \"Food & Dining\",\n    \"type\": \"expense\",\n    \"sort_order\": 1,\n    \"is_default\": false,\n    \"updated_at\": \"2025-09-07T10:27:07.000000Z\",\n    \"created_at\": \"2025-09-07T10:27:07.000000Z\",\n    \"id\": 7\n  }\n}"
						}
					]
				}
			]
		},
		{
			"name": "Budget Items",
			"item": [
				{
					"name": "Create Budget Item",
					"request": {
						"method": "POST",
						"header": [
							{
								"key": "Authorization",
								"value": "Bearer {{auth_token}}"
							},
							{
								"key": "Content-Type",
								"value": "application/json"
							}
						],
						"body": {
							"mode": "raw",
							"raw": "{\n  \"category_id\": 7,\n  \"planned_amount\": 500.00,\n  \"notes\": \"Monthly food budget\"\n}"
						},
						"url": {
							"raw": "{{base_url}}/api/budgets/{{budget_id}}/items",
							"host": [
								"{{base_url}}"
							],
							"path": [
								"api",
								"budgets",
								"{{budget_id}}",
								"items"
							]
						},
						"description": "Create a budget item (allocation) for a specific category within a budget."
					},
					"response": [
						{
							"name": "Success Response",
							"originalRequest": {
								"method": "POST",
								"header": [],
								"body": {
									"mode": "raw",
									"raw": "{\n  \"category_id\": 7,\n  \"planned_amount\": 500.00,\n  \"notes\": \"Monthly food budget\"\n}"
								},
								"url": {
									"raw": "{{base_url}}/api/budgets/6/items",
									"host": [
										"{{base_url}}"
									],
									"path": [
										"api",
										"budgets",
										"6",
										"items"
									]
								}
							},
							"status": "Created",
							"code": 201,
							"_postman_previewlanguage": "json",
							"header": [],
							"cookie": [],
							"body": "{\n  \"success\": true,\n  \"message\": \"Budget item created successfully\",\n  \"data\": {\n    \"budget_id\": 6,\n    \"category_id\": 7,\n    \"planned_amount\": \"500.00\",\n    \"notes\": \"Monthly food budget\",\n    \"updated_at\": \"2025-09-07T10:27:22.000000Z\",\n    \"created_at\": \"2025-09-07T10:27:22.000000Z\",\n    \"id\": 6,\n    \"category\": {\n      \"id\": 7,\n      \"user_id\": 1,\n      \"name\": \"Food & Dining\",\n      \"type\": \"expense\",\n      \"sort_order\": 1,\n      \"is_default\": false,\n      \"created_at\": \"2025-09-07T10:27:07.000000Z\",\n      \"updated_at\": \"2025-09-07T10:27:07.000000Z\"\n    }\n  }\n}"
						}
					]
				},
				{
					"name": "Update Budget Item",
					"request": {
						"method": "PATCH",
						"header": [
							{
								"key": "Authorization",
								"value": "Bearer {{auth_token}}"
							},
							{
								"key": "Content-Type",
								"value": "application/json"
							}
						],
						"body": {
							"mode": "raw",
							"raw": "{\n  \"planned_amount\": 600.00,\n  \"notes\": \"Updated monthly food budget\"\n}"
						},
						"url": {
							"raw": "{{base_url}}/api/budget-items/{{budget_item_id}}",
							"host": [
								"{{base_url}}"
							],
							"path": [
								"api",
								"budget-items",
								"{{budget_item_id}}"
							]
						},
						"description": "Update an existing budget item's planned amount or notes."
					}
				},
				{
					"name": "Delete Budget Item",
					"request": {
						"method": "DELETE",
						"header": [
							{
								"key": "Authorization",
								"value": "Bearer {{auth_token}}"
							},
							{
								"key": "Content-Type",
								"value": "application/json"
							}
						],
						"url": {
							"raw": "{{base_url}}/api/budget-items/{{budget_item_id}}",
							"host": [
								"{{base_url}}"
							],
							"path": [
								"api",
								"budget-items",
								"{{budget_item_id}}"
							]
						},
						"description": "Delete a budget item allocation."
					}
				}
			]
		},
		{
			"name": "Expenses (Zero-Based Integration)",
			"item": [
				{
					"name": "Get All Expenses",
					"request": {
						"method": "GET",
						"header": [
							{
								"key": "Authorization",
								"value": "Bearer {{auth_token}}"
							},
							{
								"key": "Content-Type",
								"value": "application/json"
							}
						],
						"url": {
							"raw": "{{base_url}}/api/expenses?budget_id={{budget_id}}&category_id={{category_id}}&month={{month}}",
							"host": [
								"{{base_url}}"
							],
							"path": [
								"api",
								"expenses"
							],
							"query": [
								{
									"key": "budget_id",
									"value": "{{budget_id}}",
									"description": "Filter by budget ID"
								},
								{
									"key": "category_id",
									"value": "{{category_id}}",
									"description": "Filter by category ID"
								},
								{
									"key": "month",
									"value": "{{month}}",
									"description": "Filter by month (YYYY-MM format)"
								}
							]
						},
						"description": "Retrieve expenses with filtering options. Includes budget item relationships for zero-based budgeting."
					}
				},
				{
					"name": "Create Expense (Zero-Based)",
					"request": {
						"method": "POST",
						"header": [
							{
								"key": "Authorization",
								"value": "Bearer {{auth_token}}"
							},
							{
								"key": "Content-Type",
								"value": "application/json"
							}
						],
						"body": {
							"mode": "raw",
							"raw": "{\n  \"budget_id\": 6,\n  \"category_id\": 7,\n  \"budget_item_id\": 6,\n  \"amount\": 75.50,\n  \"description\": \"Grocery shopping at Whole Foods\",\n  \"date\": \"2025-12-05\"\n}"
						},
						"url": {
							"raw": "{{base_url}}/api/expenses",
							"host": [
								"{{base_url}}"
							],
							"path": [
								"api",
								"expenses"
							]
						},
						"description": "Create a new expense linked to a budget item. The budget_item_id is REQUIRED for zero-based budgeting. System validates spending limits and budget ownership."
					}
				},
				{
					"name": "Update Expense",
					"request": {
						"method": "PUT",
						"header": [
							{
								"key": "Authorization",
								"value": "Bearer {{auth_token}}"
							},
							{
								"key": "Content-Type",
								"value": "application/json"
							}
						],
						"body": {
							"mode": "raw",
							"raw": "{\n  \"amount\": 85.00,\n  \"description\": \"Updated grocery shopping expense\",\n  \"date\": \"2025-12-05\"\n}"
						},
						"url": {
							"raw": "{{base_url}}/api/expenses/{{expense_id}}",
							"host": [
								"{{base_url}}"
							],
							"path": [
								"api",
								"expenses",
								"{{expense_id}}"
							]
						},
						"description": "Update an existing expense."
					}
				}
			]
		},
		{
			"name": "Incomes",
			"item": [
				{
					"name": "Create Income",
					"request": {
						"method": "POST",
						"header": [
							{
								"key": "Authorization",
								"value": "Bearer {{auth_token}}"
							},
							{
								"key": "Content-Type",
								"value": "application/json"
							}
						],
						"body": {
							"mode": "raw",
							"raw": "{\n  \"budget_id\": 6,\n  \"amount\": 3000.00,\n  \"description\": \"Monthly Salary\",\n  \"date\": \"2025-12-01\"\n}"
						},
						"url": {
							"raw": "{{base_url}}/api/incomes",
							"host": [
								"{{base_url}}"
							],
							"path": [
								"api",
								"incomes"
							]
						},
						"description": "Create a new income entry for a budget."
					}
				}
			]
		},
		{
			"name": "Reports & Analytics",
			"item": [
				{
					"name": "Dashboard Report",
					"request": {
						"method": "GET",
						"header": [
							{
								"key": "Authorization",
								"value": "Bearer {{auth_token}}"
							},
							{
								"key": "Content-Type",
								"value": "application/json"
							}
						],
						"url": {
							"raw": "{{base_url}}/api/reports/dashboard",
							"host": [
								"{{base_url}}"
							],
							"path": [
								"api",
								"reports",
								"dashboard"
							]
						},
						"description": "Get comprehensive dashboard data including current month metrics, recent transactions, and active budgets."
					},
					"response": [
						{
							"name": "Success Response",
							"originalRequest": {
								"method": "GET",
								"header": [],
								"url": {
									"raw": "{{base_url}}/api/reports/dashboard",
									"host": [
										"{{base_url}}"
									],
									"path": [
										"api",
										"reports",
										"dashboard"
									]
								}
							},
							"status": "OK",
							"code": 200,
							"_postman_previewlanguage": "json",
							"header": [],
							"cookie": [],
							"body": "{\n  \"success\": true,\n  \"message\": \"Dashboard data retrieved successfully\",\n  \"data\": {\n    \"current_month\": {\n      \"income\": 0,\n      \"expenses\": 0,\n      \"net\": 0\n    },\n    \"recent_expenses\": [],\n    \"recent_incomes\": [],\n    \"active_budgets\": []\n  }\n}"
						}
					]
				}
			]
		}
	],
	"variable": [
		{
			"key": "base_url",
			"value": "http://127.0.0.1:8000",
			"type": "string"
		},
		{
			"key": "auth_token",
			"value": "",
			"type": "string",
			"description": "Bearer token obtained from login"
		},
		{
			"key": "budget_id",
			"value": "6",
			"type": "string"
		},
		{
			"key": "category_id",
			"value": "7",
			"type": "string"
		},
		{
			"key": "budget_item_id",
			"value": "6",
			"type": "string"
		},
		{
			"key": "expense_id",
			"value": "",
			"type": "string"
		},
		{
			"key": "month",
			"value": "2025-12",
			"type": "string"
		}
	]
}